pyrpds-0.0.7.dist-info/METADATA
pyrpds-0.0.7.dist-info/WHEEL
pyrpds.cpython-38-x86_64-linux-gnu.so
pyrpds-0.0.7.dist-info/RECORD
