Metadata-Version: 2.1
Name: pyrpds
Version: 0.0.7
Summary: Python Wrapper for Rust Persistent Data Structures
Keywords: data-structures immutable persistent pyrsistent python
Home-Page: https://github.com/arakhmat/pyrpds/
Author: Akhmed Rakhmati <akhmed.rakhmati@gmail.com>
Author-Email: Akhmed Rakhmati <akhmed.rakhmati@gmail.com>
